[{"t_makink": {"code": "1446", "name": "\u5b8f\u548c", "date": "29", "price": -0.15, "change": -0.51, "pct": 92.0, "volume": 0.0, "ma5": "29.21\u2198", "ma10": "29.68\u2198", "ma20": "30.13\u2198", "ma30": "30.13\u2198", "ma60": "31.16\u2198", "ma240": "30.09\u2197", "ma480": "30.73\u2197", "ma720": "28.64\u2197", "ma1200": "25.39\u2197", "ma2400": "24.2\u2197"}}, {"t_makink": {"code": "2034", "name": "\u5141\u5f37", "date": "27", "price": 0.15, "change": 0.56, "pct": 1764.0, "volume": 0.0, "ma5": "26.98\u2197", "ma10": "26.67\u2197", "ma20": "26.62\u2197", "ma30": "26.62\u2198", "ma60": "25.43\u2197", "ma240": "24.56\u2197", "ma480": "25.28\u2197", "ma720": "25.43\u2197", "ma1200": "25.34\u2197", "ma2400": "22.99\u2197"}}, {"t_makink": {"code": "1521", "name": "\u5927\u5104", "date": "53.4", "price": 0.2, "change": 0.38, "pct": 77.0, "volume": 0.0, "ma5": "53.18\u2198", "ma10": "54.08\u2198", "ma20": "54.52\u2198", "ma30": "54.52\u2198", "ma60": "54.67\u2197", "ma240": "55.97\u2197", "ma480": "59.4\u2198", "ma720": "62.29\u2198", "ma1200": "69.59\u2198", "ma2400": "67.57\u2198"}}, {"t_makink": {"code": "00744B", "name": "\u570b\u6cf0\u4e2d\u570b\u653f\u91d1\u50b55+", "date": "41.4", "price": 0.13, "change": 0.31, "pct": 101.0, "volume": 0.0, "ma5": "41.36\u2198", "ma10": "41.38\u2197", "ma20": "41.18\u2197", "ma30": "41.18\u2197", "ma60": "40.99\u2197", "ma240": "41.03\u2198", "ma480": "41.44\u2198", "ma720": "", "ma1200": "", "ma2400": ""}}, {"t_makink": {"code": "8467", "name": "\u6ce2\u529b-KY", "date": "46.8", "price": 0.05, "change": 0.11, "pct": 2.0, "volume": 0.0, "ma5": "47.49\u2198", "ma10": "47.34\u2198", "ma20": "46.75\u2197", "ma30": "46.74\u2198", "ma60": "47.9\u2198", "ma240": "48.99\u2197", "ma480": "50.29\u2197", "ma720": "43.83\u2197", "ma1200": "42.11\u2198", "ma2400": ""}}, {"t_makink": {"code": "2201", "name": "\u88d5\u9686", "date": "44.45", "price": 0.4, "change": 0.91, "pct": 9678.0, "volume": 0.0, "ma5": "43.71\u2198", "ma10": "43.73\u2197", "ma20": "43.03\u2197", "ma30": "43.02\u2197", "ma60": "38.65\u2197", "ma240": "29.68\u2197", "ma480": "25.06\u2197", "ma720": "23.58\u2197", "ma1200": "24.89\u2197", "ma2400": "37.28\u2198"}}, {"t_makink": {"code": "2801", "name": "\u5f70\u9280", "date": "17.5", "price": -0.05, "change": -0.28, "pct": 5730.0, "volume": 0.0, "ma5": "17.49\u2197", "ma10": "17.35\u2197", "ma20": "17.31\u2197", "ma30": "17.32\u2197", "ma60": "17.41\u2197", "ma240": "18.22\u2198", "ma480": "19.67\u2198", "ma720": "19.03\u2197", "ma1200": "18.17\u2197", "ma2400": "17.99\u2198"}}, {"t_makink": {"code": "2417", "name": "\u5713\u525b", "date": "50.1", "price": 2.15, "change": 4.48, "pct": 9752.0, "volume": 0.0, "ma5": "47.41\u2197", "ma10": "48.35\u2197", "ma20": "47.12\u2197", "ma30": "47.11\u2197", "ma60": "53\u2198", "ma240": "42.61\u2197", "ma480": "26.76\u2197", "ma720": "21.74\u2197", "ma1200": "17.42\u2197", "ma2400": "17.26\u2197"}}, {"t_makink": {"code": "3443", "name": "\u5275\u610f", "date": "413.5", "price": 15.0, "change": 3.76, "pct": 5073.0, "volume": 0.0, "ma5": "399.3\u2197", "ma10": "396.6\u2198", "ma20": "404\u2198", "ma30": "403.9\u2197", "ma60": "350.4\u2197", "ma240": "303\u2197", "ma480": "269.1\u2197", "ma720": "263.9\u2197", "ma1200": "215.2\u2197", "ma2400": "153.4\u2197"}}, {"t_makink": {"code": "2608", "name": "\u5609\u91cc\u5927\u69ae", "date": "44.1", "price": -0.1, "change": -0.23, "pct": 91.0, "volume": 0.0, "ma5": "43.76\u2197", "ma10": "43.04\u2197", "ma20": "43.09\u2197", "ma30": "43.08\u2197", "ma60": "41.85\u2197", "ma240": "40.99\u2197", "ma480": "39.26\u2197", "ma720": "38.96\u2197", "ma1200": "39.49\u2197", "ma2400": "38.67\u2197"}}, {"t_makink": {"code": "6418", "name": "\u8a60\u6607", "date": "14.15", "price": -0.4, "change": -2.75, "pct": 32.0, "volume": 0.0, "ma5": "14.35\u2198", "ma10": "14.37\u2198", "ma20": "14.3\u2198", "ma30": "14.3\u2198", "ma60": "14.62\u2198", "ma240": "14.45\u2197", "ma480": "17.2\u2198", "ma720": "", "ma1200": "", "ma2400": ""}}, {"t_makink": {"code": "8349", "name": "\u6052\u8000", "date": "70.7", "price": -0.1, "change": -0.14, "pct": 258.0, "volume": 0.0, "ma5": "70.94\u2198", "ma10": "70.72\u2197", "ma20": "70.3\u2198", "ma30": "70.33\u2197", "ma60": "63.72\u2197", "ma240": "55.06\u2197", "ma480": "60.69\u2198", "ma720": "71.23\u2198", "ma1200": "80.01\u2198", "ma2400": "67.46\u2197"}}, {"t_makink": {"code": "1589", "name": "\u6c38\u51a0-KY", "date": "79.5", "price": -0.5, "change": -0.62, "pct": 450.0, "volume": 0.0, "ma5": "79.12\u2197", "ma10": "78.84\u2198", "ma20": "80.45\u2198", "ma30": "80.42\u2198", "ma60": "85.47\u2198", "ma240": "80.2\u2197", "ma480": "70.64\u2197", "ma720": "67.16\u2197", "ma1200": "89.11\u2198", "ma2400": ""}}, {"t_makink": {"code": "4741", "name": "\u6cd3\u701a", "date": "27.15", "price": -0.2, "change": -0.73, "pct": 10.0, "volume": 0.0, "ma5": "27.28\u2197", "ma10": "27.22\u2198", "ma20": "27.22\u2198", "ma30": "27.21\u2198", "ma60": "27.7\u2198", "ma240": "27.78\u2197", "ma480": "29.83\u2198", "ma720": "36.36\u2198", "ma1200": "", "ma2400": ""}}, {"t_makink": {"code": "8415", "name": "\u5927\u570b\u92fc", "date": "27.35", "price": 0.2, "change": 0.74, "pct": 1476.0, "volume": 0.0, "ma5": "26.9\u2197", "ma10": "26.42\u2197", "ma20": "26.55\u2197", "ma30": "26.54\u2198", "ma60": "26.56\u2197", "ma240": "26.37\u2197", "ma480": "29.39\u2198", "ma720": "30.23\u2197", "ma1200": "", "ma2400": ""}}, {"t_makink": {"code": "8050", "name": "\u5ee3\u7a4d", "date": "38.05", "price": 0.0, "change": 0.0, "pct": 331.0, "volume": 0.0, "ma5": "37.57\u2197", "ma10": "37.35\u2197", "ma20": "36.94\u2197", "ma30": "36.95\u2197", "ma60": "38.5\u2198", "ma240": "39.52\u2197", "ma480": "41.24\u2198", "ma720": "41.59\u2198", "ma1200": "48.55\u2198", "ma2400": "48.05\u2198"}}, {"t_makink": {"code": "2002A", "name": "\u4e2d\u92fc\u7279", "date": "51", "price": 0.0, "change": 0.0, "pct": 26.0, "volume": 0.0, "ma5": "51\u2192", "ma10": "51\u2198", "ma20": "51.03\u2192", "ma30": "51.01\u2192", "ma60": "50.91\u2198", "ma240": "52.28\u2197", "ma480": "51.15\u2197", "ma720": "48.47\u2197", "ma1200": "45.78\u2197", "ma2400": "43.01\u2197"}}, {"t_makink": {"code": "2809", "name": "\u4eac\u57ce\u9280", "date": "39.4", "price": 0.0, "change": 0.0, "pct": 1034.0, "volume": 0.0, "ma5": "39.24\u2197", "ma10": "39.12\u2197", "ma20": "39.07\u2197", "ma30": "39.05\u2197", "ma60": "38.81\u2197", "ma240": "36.57\u2197", "ma480": "34.68\u2197", "ma720": "33.83\u2197", "ma1200": "32.01\u2197", "ma2400": "28.19\u2197"}}, {"t_makink": {"code": "00794B", "name": "\u7fa4\u76ca7+\u4e2d\u570b\u653f\u91d1\u50b5", "date": "39.59", "price": 0.2, "change": 0.51, "pct": 101.0, "volume": 0.0, "ma5": "39.53\u2198", "ma10": "39.55\u2197", "ma20": "39.3\u2197", "ma30": "39.32\u2197", "ma60": "39.13\u2197", "ma240": "39.22\u2198", "ma480": "", "ma720": "", "ma1200": "", "ma2400": ""}}, {"t_makink": {"code": "3376", "name": "\u65b0\u65e5\u8208", "date": "130.5", "price": -1.0, "change": -0.76, "pct": 667.0, "volume": 0.0, "ma5": "129.9\u2197", "ma10": "128.9\u2198", "ma20": "129.2\u2197", "ma30": "129.2\u2198", "ma60": "136.2\u2198", "ma240": "139.2\u2197", "ma480": "130.8\u2197", "ma720": "116.3\u2197", "ma1200": "106.9\u2197", "ma2400": "93.48\u2197"}}, {"t_makink": {"code": "2538", "name": "\u57fa\u6cf0", "date": "10", "price": 0.0, "change": 0.0, "pct": 645.0, "volume": 0.0, "ma5": "10.03\u2198", "ma10": "10.04\u2198", "ma20": "10.07\u2192", "ma30": "10.06\u2198", "ma60": "10.03\u2192", "ma240": "9.95\u2197", "ma480": "10.92\u2198", "ma720": "11.18\u2198", "ma1200": "11.27\u2198", "ma2400": "14.81\u2198"}}, {"t_makink": {"code": "2049", "name": "\u4e0a\u9280", "date": "404.5", "price": 2.0, "change": 0.5, "pct": 1059.0, "volume": 0.0, "ma5": "403.8\u2197", "ma10": "403.8\u2198", "ma20": "414\u2198", "ma30": "414.2\u2197", "ma60": "356.3\u2197", "ma240": "325.1\u2197", "ma480": "296.7\u2197", "ma720": "299.5\u2197", "ma1200": "263.9\u2197", "ma2400": "252.9\u2197"}}, {"t_makink": {"code": "8480", "name": "\u6cf0\u6607-KY", "date": "120", "price": -0.5, "change": -0.41, "pct": 41.0, "volume": 0.0, "ma5": "120.2\u2197", "ma10": "119.6\u2198", "ma20": "120.3\u2198", "ma30": "120.2\u2197", "ma60": "120.4\u2192", "ma240": "124.3\u2198", "ma480": "126.9\u2198", "ma720": "128.5\u2198", "ma1200": "", "ma2400": ""}}, {"t_makink": {"code": "4188", "name": "\u5b89\u514b", "date": "19.15", "price": 0.0, "change": 0.0, "pct": 29.0, "volume": 0.0, "ma5": "19.27\u2198", "ma10": "19.33\u2197", "ma20": "19.24\u2198", "ma30": "19.23\u2198", "ma60": "19.54\u2198", "ma240": "20.26\u2197", "ma480": "22.13\u2198", "ma720": "24.69\u2198", "ma1200": "27.17\u2198", "ma2400": ""}}, {"t_makink": {"code": "3115", "name": "\u5bf6\u5cf6\u6975", "date": "16.2", "price": 0.55, "change": 3.51, "pct": 20.0, "volume": 0.0, "ma5": "15.92\u2197", "ma10": "16.1\u2198", "ma20": "16.54\u2198", "ma30": "16.53\u2197", "ma60": "15.85\u2198", "ma240": "14.39\u2197", "ma480": "15.29\u2198", "ma720": "18.06\u2197", "ma1200": "15.73\u2197", "ma2400": "14.18\u2197"}}, {"t_makink": {"code": "1465", "name": "\u5049\u5168", "date": "13.2", "price": 0.3, "change": 2.33, "pct": 268.0, "volume": 0.0, "ma5": "13.01\u2197", "ma10": "12.91\u2197", "ma20": "12.89\u2197", "ma30": "12.88\u2197", "ma60": "12.93\u2198", "ma240": "13.98\u2198", "ma480": "14.3\u2198", "ma720": "14.3\u2198", "ma1200": "14.16\u2198", "ma2400": "14.88\u2198"}}, {"t_makink": {"code": "8463", "name": "\u6f64\u6cf0\u6750", "date": "36.95", "price": -0.2, "change": -0.54, "pct": 64.0, "volume": 0.0, "ma5": "37.25\u2197", "ma10": "36.58\u2197", "ma20": "36.43\u2197", "ma30": "36.45\u2198", "ma60": "36.51\u2198", "ma240": "36.87\u2197", "ma480": "35.03\u2197", "ma720": "32.18\u2197", "ma1200": "26.62\u2197", "ma2400": ""}}, {"t_makink": {"code": "00736", "name": "\u570b\u6cf0\u65b0\u8208\u5e02\u5834", "date": "23.61", "price": 0.19, "change": 0.81, "pct": 118.0, "volume": 0.0, "ma5": "23.44\u2197", "ma10": "23.39\u2198", "ma20": "23.45\u2198", "ma30": "23.46\u2197", "ma60": "22.25\u2197", "ma240": "20.43\u2197", "ma480": "20.08\u2197", "ma720": "", "ma1200": "", "ma2400": ""}}, {"t_makink": {"code": "00843B", "name": "\u53f0\u65b0\u4e2d\u570b\u653f\u7b56\u50b5", "date": "38.97", "price": 0.09, "change": 0.23, "pct": 100.0, "volume": 0.0, "ma5": "39.01\u2198", "ma10": "39.06\u2197", "ma20": "38.86\u2197", "ma30": "38.83\u2197", "ma60": "38.65\u2197", "ma240": "38.66\u2198", "ma480": "", "ma720": "", "ma1200": "", "ma2400": ""}}, {"t_makink": {"code": "2891C", "name": "\u4e2d\u4fe1\u91d1\u4e19\u7279", "date": "61.8", "price": 0.0, "change": 0.0, "pct": 13.0, "volume": 0.0, "ma5": "61.74\u2197", "ma10": "61.72\u2197", "ma20": "61.74\u2197", "ma30": "61.68\u2197", "ma60": "61.99\u2198", "ma240": "62.52\u2197", "ma480": "", "ma720": "", "ma1200": "", "ma2400": ""}}, {"t_makink": {"code": "4744", "name": "\u7687\u5c07", "date": "29.2", "price": -0.05, "change": -0.17, "pct": 91.0, "volume": 0.0, "ma5": "29.13\u2197", "ma10": "29.01\u2197", "ma20": "29.01\u2197", "ma30": "29.04\u2197", "ma60": "30.19\u2198", "ma240": "32.3\u2198", "ma480": "32.26\u2198", "ma720": "", "ma1200": "", "ma2400": ""}}, {"t_makink": {"code": "2891B", "name": "\u4e2d\u4fe1\u91d1\u4e59\u7279", "date": "63.5", "price": 0.0, "change": 0.0, "pct": 3.0, "volume": 0.0, "ma5": "63.5\u2192", "ma10": "63.49\u2192", "ma20": "63.55\u2198", "ma30": "63.49\u2197", "ma60": "63.85\u2198", "ma240": "64.9\u2197", "ma480": "64.9\u2198", "ma720": "64.06\u2197", "ma1200": "", "ma2400": ""}}, {"t_makink": {"code": "2395", "name": "\u7814\u83ef", "date": "353.5", "price": -0.5, "change": -0.14, "pct": 393.0, "volume": 0.0, "ma5": "355.6\u2198", "ma10": "354.4\u2198", "ma20": "357.2\u2198", "ma30": "356.8\u2197", "ma60": "330.5\u2197", "ma240": "312.6\u2197", "ma480": "294.1\u2197", "ma720": "267.3\u2197", "ma1200": "255.4\u2197", "ma2400": "207.8\u2197"}}, {"t_makink": {"code": "2888B", "name": "\u65b0\u5149\u91d1\u4e59\u7279", "date": "41.8", "price": -0.1, "change": -0.24, "pct": 458.0, "volume": 0.0, "ma5": "41.93\u2198", "ma10": "41.92\u2198", "ma20": "41.92\u2197", "ma30": "41.88\u2198", "ma60": "42.13\u2198", "ma240": "", "ma480": "", "ma720": "", "ma1200": "", "ma2400": ""}}, {"t_makink": {"code": "1410", "name": "\u5357\u67d3", "date": "34", "price": 0.1, "change": 0.29, "pct": 6.0, "volume": 0.0, "ma5": "33.99\u2198", "ma10": "33.92\u2197", "ma20": "33.85\u2197", "ma30": "33.88\u2197", "ma60": "33.8\u2197", "ma240": "32.95\u2197", "ma480": "30.49\u2197", "ma720": "28.22\u2197", "ma1200": "26.68\u2197", "ma2400": "24.12\u2197"}}, {"t_makink": {"code": "1795", "name": "\u7f8e\u6642", "date": "77.8", "price": 0.1, "change": 0.13, "pct": 905.0, "volume": 0.0, "ma5": "76.56\u2197", "ma10": "75.3\u2197", "ma20": "74.4\u2197", "ma30": "74.48\u2198", "ma60": "78.69\u2198", "ma240": "78.43\u2197", "ma480": "90.24\u2198", "ma720": "84.55\u2197", "ma1200": "73.3\u2197", "ma2400": "68.96\u2197"}}, {"t_makink": {"code": "6124", "name": "\u696d\u5f37", "date": "29.5", "price": 0.1, "change": 0.34, "pct": 13.0, "volume": 0.0, "ma5": "29.5\u2198", "ma10": "29.72\u2198", "ma20": "29.89\u2198", "ma30": "29.85\u2198", "ma60": "30.17\u2198", "ma240": "30.91\u2197", "ma480": "34.28\u2197", "ma720": "30.28\u2197", "ma1200": "28.99\u2197", "ma2400": "27.82\u2198"}}, {"t_makink": {"code": "1233", "name": "\u5929\u4ec1", "date": "35.15", "price": 0.0, "change": 0.0, "pct": 18.0, "volume": 0.0, "ma5": "35.08\u2197", "ma10": "35.06\u2198", "ma20": "35.08\u2197", "ma30": "35.05\u2198", "ma60": "35.53\u2198", "ma240": "35.89\u2197", "ma480": "37.11\u2198", "ma720": "37.4\u2198", "ma1200": "37.06\u2198", "ma2400": "41.98\u2198"}}, {"t_makink": {"code": "020023", "name": "\u5143\u5927\u6ac3\u8cb7\u534a\u5c0e\u9ad4N", "date": "5.7", "price": 0.0, "change": 0.0, "pct": 947.0, "volume": 0.0, "ma5": "5.67\u2197", "ma10": "5.6\u2197", "ma20": "5.55\u2197", "ma30": "5.55\u2197", "ma60": "", "ma240": "", "ma480": "", "ma720": "", "ma1200": "", "ma2400": ""}}, {"t_makink": {"code": "00879B", "name": "\u7b2c\u4e00\u91d1\u7f8e\u50b50-1", "date": "37.47", "price": -0.13, "change": -0.35, "pct": 100.0, "volume": 0.0, "ma5": "37.59\u2198", "ma10": "37.64\u2198", "ma20": "37.47\u2197", "ma30": "37.42\u2198", "ma60": "37.85\u2198", "ma240": "", "ma480": "", "ma720": "", "ma1200": "", "ma2400": ""}}, {"t_makink": {"code": "5309", "name": "\u7cfb\u7d71\u96fb", "date": "40.15", "price": 1.95, "change": 5.1, "pct": 3538.0, "volume": 0.0, "ma5": "38.99\u2197", "ma10": "38.73\u2198", "ma20": "39.61\u2198", "ma30": "39.66\u2198", "ma60": "40.99\u2197", "ma240": "35.07\u2197", "ma480": "22.06\u2197", "ma720": "17.19\u2197", "ma1200": "14.88\u2197", "ma2400": "13.21\u2197"}}, {"t_makink": {"code": "4736", "name": "\u6cf0\u535a", "date": "184", "price": -1.5, "change": -0.81, "pct": 403.0, "volume": 0.0, "ma5": "185.7\u2197", "ma10": "184.2\u2197", "ma20": "184.1\u2198", "ma30": "183.9\u2198", "ma60": "195.1\u2198", "ma240": "212.4\u2197", "ma480": "176.4\u2197", "ma720": "169\u2197", "ma1200": "145.1\u2197", "ma2400": "109\u2197"}}, {"t_makink": {"code": "2701", "name": "\u842c\u4f01", "date": "12.05", "price": -0.05, "change": -0.41, "pct": 95.0, "volume": 0.0, "ma5": "12\u2197", "ma10": "11.98\u2197", "ma20": "12\u2192", "ma30": "11.98\u2197", "ma60": "11.91\u2197", "ma240": "11.92\u2197", "ma480": "12.47\u2198", "ma720": "12.59\u2198", "ma1200": "13.08\u2198", "ma2400": "13.85\u2198"}}, {"t_makink": {"code": "5310", "name": "\u5929\u525b", "date": "16.6", "price": 1.5, "change": 9.93, "pct": 667.0, "volume": 0.0, "ma5": "14.08\u2197", "ma10": "13.2\u2197", "ma20": "12.74\u2197", "ma30": "12.72\u2197", "ma60": "13.29\u2197", "ma240": "12.7\u2197", "ma480": "18.83\u2198", "ma720": "28.53\u2198", "ma1200": "28.05\u2198", "ma2400": "30.98\u2198"}}, {"t_makink": {"code": "1414", "name": "\u6771\u548c", "date": "13.8", "price": -0.3, "change": -2.13, "pct": 2459.0, "volume": 0.0, "ma5": "14.23\u2197", "ma10": "13.34\u2197", "ma20": "12.98\u2197", "ma30": "13\u2198", "ma60": "12.92\u2197", "ma240": "9.91\u2197", "ma480": "8.4\u2197", "ma720": "8.07\u2197", "ma1200": "7.43\u2197", "ma2400": "8.55\u2198"}}, {"t_makink": {"code": "6015", "name": "\u5b8f\u9060\u8b49", "date": "13.15", "price": 0.1, "change": 0.77, "pct": 2940.0, "volume": 0.0, "ma5": "12.91\u2197", "ma10": "12.74\u2197", "ma20": "12.34\u2197", "ma30": "12.33\u2197", "ma60": "10.02\u2197", "ma240": "8.55\u2197", "ma480": "7.5\u2197", "ma720": "7.28\u2197", "ma1200": "7.09\u2197", "ma2400": "7.44\u2197"}}, {"t_makink": {"code": "2316", "name": "\u6960\u6893\u96fb", "date": "31.45", "price": 0.1, "change": 0.32, "pct": 597.0, "volume": 0.0, "ma5": "31.73\u2197", "ma10": "31.49\u2197", "ma20": "30.91\u2197", "ma30": "30.95\u2197", "ma60": "30.57\u2197", "ma240": "30.44\u2197", "ma480": "30.59\u2197", "ma720": "25.8\u2197", "ma1200": "23.76\u2197", "ma2400": "20.01\u2197"}}, {"t_makink": {"code": "2516", "name": "\u65b0\u5efa", "date": "4.98", "price": -0.01, "change": -0.2, "pct": 187.0, "volume": 0.0, "ma5": "4.99\u2198", "ma10": "4.99\u2198", "ma20": "5\u2198", "ma30": "5\u2198", "ma60": "5.12\u2198", "ma240": "5.04\u2197", "ma480": "5.48\u2198", "ma720": "5.77\u2198", "ma1200": "6.17\u2198", "ma2400": "7.4\u2198"}}, {"t_makink": {"code": "9908", "name": "\u5927\u53f0\u5317", "date": "33.75", "price": 0.1, "change": 0.3, "pct": 114.0, "volume": 0.0, "ma5": "33.68\u2197", "ma10": "33.58\u2197", "ma20": "33.66\u2198", "ma30": "33.61\u2198", "ma60": "33\u2197", "ma240": "31.76\u2197", "ma480": "30.98\u2197", "ma720": "30.08\u2197", "ma1200": "27.95\u2197", "ma2400": "24.58\u2197"}}, {"t_makink": {"code": "2881A", "name": "\u5bcc\u90a6\u7279", "date": "62", "price": 0.0, "change": 0.0, "pct": 346.0, "volume": 0.0, "ma5": "62\u2192", "ma10": "62\u2197", "ma20": "62.04\u2192", "ma30": "61.95\u2197", "ma60": "61.97\u2198", "ma240": "62.95\u2197", "ma480": "64.01\u2198", "ma720": "64.16\u2198", "ma1200": "", "ma2400": ""}}, {"t_makink": {"code": "6510", "name": "\u7cbe\u6e2c", "date": "909", "price": 0.0, "change": 0.0, "pct": 146.0, "volume": 0.0, "ma5": "908.8\u2197", "ma10": "893.7\u2197", "ma20": "874.4\u2197", "ma30": "875.7\u2197", "ma60": "804.7\u2197", "ma240": "763.1\u2197", "ma480": "728.6\u2197", "ma720": "688.4\u2198", "ma1200": "", "ma2400": ""}}, {"t_makink": {"code": "3594", "name": "\u78d0\u5100", "date": "25.35", "price": -0.1, "change": -0.39, "pct": 162.0, "volume": 0.0, "ma5": "25.56\u2198", "ma10": "25.42\u2197", "ma20": "25\u2197", "ma30": "24.96\u2197", "ma60": "24.59\u2198", "ma240": "23.41\u2197", "ma480": "23.24\u2197", "ma720": "23.32\u2198", "ma1200": "24.68\u2198", "ma2400": ""}}, {"t_makink": {"code": "8028", "name": "\u6607\u967d\u534a\u5c0e\u9ad4", "date": "53.5", "price": 0.1, "change": 0.19, "pct": 539.0, "volume": 0.0, "ma5": "53.46\u2197", "ma10": "53.73\u2198", "ma20": "54.4\u2198", "ma30": "54.32\u2198", "ma60": "53.01\u2197", "ma240": "51.77\u2197", "ma480": "56.72\u2197", "ma720": "", "ma1200": "", "ma2400": ""}}, {"t_makink": {"code": "1717", "name": "\u9577\u8208", "date": "36.25", "price": 0.3, "change": 0.83, "pct": 4254.0, "volume": 0.0, "ma5": "36.04\u2197", "ma10": "35.83\u2197", "ma20": "35.56\u2197", "ma30": "35.5\u2198", "ma60": "34.9\u2197", "ma240": "32.99\u2197", "ma480": "29.42\u2197", "ma720": "28.38\u2197", "ma1200": "30.04\u2197", "ma2400": "29.12\u2197"}}, {"t_makink": {"code": "2543", "name": "\u7687\u660c", "date": "6.91", "price": 0.05, "change": 0.73, "pct": 168.0, "volume": 0.0, "ma5": "6.94\u2198", "ma10": "6.97\u2198", "ma20": "7\u2198", "ma30": "7.01\u2198", "ma60": "7.04\u2198", "ma240": "6.82\u2198", "ma480": "7.09\u2198", "ma720": "7.37\u2198", "ma1200": "8.04\u2198", "ma2400": "7.98\u2197"}}, {"t_makink": {"code": "3523", "name": "\u8fce\u8f1d", "date": "11.55", "price": 0.0, "change": 0.0, "pct": 93.0, "volume": 0.0, "ma5": "11.56\u2197", "ma10": "11.56\u2198", "ma20": "11.71\u2198", "ma30": "11.73\u2198", "ma60": "12.43\u2198", "ma240": "12.87\u2197", "ma480": "12.3\u2198", "ma720": "11.73\u2197", "ma1200": "12.98\u2198", "ma2400": "19.14\u2198"}}, {"t_makink": {"code": "6461", "name": "\u76ca\u5f97", "date": "20.15", "price": -0.15, "change": -0.74, "pct": 171.0, "volume": 0.0, "ma5": "20.29\u2197", "ma10": "20.17\u2198", "ma20": "20.32\u2198", "ma30": "20.28\u2198", "ma60": "20.33\u2198", "ma240": "20.21\u2197", "ma480": "20.04\u2198", "ma720": "", "ma1200": "", "ma2400": ""}}, {"t_makink": {"code": "3563", "name": "\u7267\u5fb7", "date": "285", "price": 0.5, "change": 0.18, "pct": 95.0, "volume": 0.0, "ma5": "286.8\u2198", "ma10": "285.1\u2197", "ma20": "281.3\u2197", "ma30": "281.8\u2197", "ma60": "286.8\u2198", "ma240": "296.6\u2197", "ma480": "326.1\u2198", "ma720": "352.3\u2198", "ma1200": "255.7\u2197", "ma2400": "154.9\u2197"}}, {"t_makink": {"code": "6121", "name": "\u65b0\u666e", "date": "371.5", "price": 0.5, "change": 0.13, "pct": 782.0, "volume": 0.0, "ma5": "369.7\u2197", "ma10": "368.4\u2198", "ma20": "363.7\u2198", "ma30": "364.3\u2197", "ma60": "345\u2197", "ma240": "333.6\u2197", "ma480": "303.7\u2197", "ma720": "266.9\u2197", "ma1200": "207.9\u2197", "ma2400": "184.2\u2197"}}, {"t_makink": {"code": "1101B", "name": "\u53f0\u6ce5\u4e59\u7279", "date": "53.8", "price": 0.0, "change": 0.0, "pct": 1.0, "volume": 0.0, "ma5": "53.7\u2192", "ma10": "53.66\u2197", "ma20": "53.62\u2192", "ma30": "53.72\u2197", "ma60": "53.69\u2198", "ma240": "53.97\u2197", "ma480": "53.54\u2197", "ma720": "", "ma1200": "", "ma2400": ""}}, {"t_makink": {"code": "2882A", "name": "\u570b\u6cf0\u7279", "date": "61.7", "price": -0.1, "change": -0.16, "pct": 97.0, "volume": 0.0, "ma5": "61.74\u2198", "ma10": "61.74\u2198", "ma20": "61.79\u2198", "ma30": "61.91\u2198", "ma60": "61.99\u2198", "ma240": "62.53\u2197", "ma480": "63.1\u2198", "ma720": "63.24\u2198", "ma1200": "", "ma2400": ""}}, {"t_makink": {"code": "5258", "name": "\u8679\u5821", "date": "22.35", "price": 0.4, "change": 1.82, "pct": 384.0, "volume": 0.0, "ma5": "21.97\u2197", "ma10": "22.08\u2197", "ma20": "21.75\u2197", "ma30": "21.8\u2197", "ma60": "21.79\u2197", "ma240": "22.47\u2197", "ma480": "23.4\u2197", "ma720": "21.51\u2198", "ma1200": "", "ma2400": ""}}, {"t_makink": {"code": "6593", "name": "\u53f0\u7063\u9298\u677f", "date": "25.7", "price": -0.3, "change": -1.15, "pct": 11.0, "volume": 0.0, "ma5": "25.88\u2198", "ma10": "25.92\u2198", "ma20": "25.75\u2197", "ma30": "25.7\u2198", "ma60": "25.81\u2198", "ma240": "25.12\u2197", "ma480": "26.29\u2198", "ma720": "27.41\u2198", "ma1200": "", "ma2400": ""}}, {"t_makink": {"code": "5907", "name": "\u5927\u6d0b-KY", "date": "20.65", "price": 0.25, "change": 1.23, "pct": 549.0, "volume": 0.0, "ma5": "20.23\u2197", "ma10": "20.14\u2197", "ma20": "20.17\u2197", "ma30": "20.13\u2198", "ma60": "20.97\u2198", "ma240": "22.29\u2197", "ma480": "25.9\u2198", "ma720": "27.84\u2198", "ma1200": "26.16\u2198", "ma2400": ""}}, {"t_makink": {"code": "8466", "name": "\u7f8e\u5409\u5409-KY", "date": "63.5", "price": 0.2, "change": 0.32, "pct": 62.0, "volume": 0.0, "ma5": "63.24\u2197", "ma10": "62.95\u2197", "ma20": "62.47\u2197", "ma30": "62.34\u2198", "ma60": "62.92\u2197", "ma240": "64.43\u2197", "ma480": "68.18\u2197", "ma720": "66.75\u2198", "ma1200": "", "ma2400": ""}}, {"t_makink": {"code": "5481", "name": "\u65b0\u83ef", "date": "13.7", "price": 0.0, "change": 0.0, "pct": 170.0, "volume": 0.0, "ma5": "13.79\u2197", "ma10": "13.79\u2198", "ma20": "14.09\u2198", "ma30": "14.06\u2198", "ma60": "14.8\u2198", "ma240": "14.14\u2197", "ma480": "15.45\u2198", "ma720": "17.26\u2198", "ma1200": "17.86\u2198", "ma2400": "15.14\u2198"}}, {"t_makink": {"code": "9927", "name": "\u6cf0\u9298", "date": "29.75", "price": -0.05, "change": -0.17, "pct": 176.0, "volume": 0.0, "ma5": "29.59\u2197", "ma10": "29.62\u2198", "ma20": "29.96\u2198", "ma30": "30.02\u2197", "ma60": "29.31\u2197", "ma240": "29.55\u2197", "ma480": "30.51\u2198", "ma720": "32.14\u2198", "ma1200": "33.49\u2198", "ma2400": "33.32\u2198"}}, {"t_makink": {"code": "2344", "name": "\u83ef\u90a6\u96fb", "date": "30.6", "price": 1.1, "change": 3.73, "pct": 251282.0, "volume": 0.0, "ma5": "29.72\u2197", "ma10": "28.95\u2197", "ma20": "28.31\u2197", "ma30": "28.37\u2197", "ma60": "23.38\u2197", "ma240": "18.26\u2197", "ma480": "17.47\u2197", "ma720": "17.13\u2197", "ma1200": "16.5\u2197", "ma2400": "11.99\u2197"}}, {"t_makink": {"code": "8930", "name": "\u9752\u92fc", "date": "13.65", "price": -0.05, "change": -0.36, "pct": 78.0, "volume": 0.0, "ma5": "13.86\u2198", "ma10": "13.86\u2198", "ma20": "13.96\u2198", "ma30": "13.93\u2198", "ma60": "13.37\u2197", "ma240": "12.37\u2197", "ma480": "12.63\u2197", "ma720": "13.35\u2198", "ma1200": "13.04\u2197", "ma2400": "13.14\u2198"}}, {"t_makink": {"code": "4935", "name": "\u8302\u6797-KY", "date": "105.5", "price": -1.5, "change": -1.4, "pct": 806.0, "volume": 0.0, "ma5": "106.2\u2197", "ma10": "105.7\u2198", "ma20": "105.7\u2197", "ma30": "105.5\u2198", "ma60": "107.9\u2198", "ma240": "116\u2197", "ma480": "98.4\u2197", "ma720": "77.56\u2197", "ma1200": "69.46\u2197", "ma2400": ""}}, {"t_makink": {"code": "1342", "name": "\u516b\u8cab", "date": "56.8", "price": -0.1, "change": -0.18, "pct": 25.0, "volume": 0.0, "ma5": "56.72\u2197", "ma10": "57.01\u2198", "ma20": "57.88\u2198", "ma30": "58\u2198", "ma60": "", "ma240": "", "ma480": "", "ma720": "", "ma1200": "", "ma2400": ""}}, {"t_makink": {"code": "00747B", "name": "FH\u4e2d\u570b\u653f\u7b56\u50b5", "date": "51.25", "price": 0.1, "change": 0.2, "pct": 101.0, "volume": 0.0, "ma5": "51.26\u2198", "ma10": "51.34\u2192", "ma20": "51.04\u2197", "ma30": "50.93\u2197", "ma60": "50.64\u2197", "ma240": "50.53\u2198", "ma480": "51.13\u2198", "ma720": "", "ma1200": "", "ma2400": ""}}, {"t_makink": {"code": "2481", "name": "\u5f37\u8302", "date": "54.5", "price": 1.0, "change": 1.87, "pct": 36834.0, "volume": 0.0, "ma5": "54.06\u2197", "ma10": "53.82\u2197", "ma20": "53.01\u2197", "ma30": "52.89\u2197", "ma60": "46.59\u2197", "ma240": "37.58\u2197", "ma480": "31.85\u2197", "ma720": "34.16\u2197", "ma1200": "28.58\u2197", "ma2400": "22.02\u2197"}}, {"t_makink": {"code": "1437", "name": "\u52e4\u76ca\u63a7", "date": "24.25", "price": 0.15, "change": 0.62, "pct": 168.0, "volume": 0.0, "ma5": "24.02\u2197", "ma10": "23.96\u2197", "ma20": "23.83\u2197", "ma30": "23.78\u2197", "ma60": "23.8\u2197", "ma240": "22.76\u2197", "ma480": "22.53\u2197", "ma720": "21.22\u2197", "ma1200": "19.29\u2197", "ma2400": "17.93\u2197"}}, {"t_makink": {"code": "3413", "name": "\u4eac\u9f0e", "date": "235", "price": 2.0, "change": 0.86, "pct": 2659.0, "volume": 0.0, "ma5": "239.6\u2198", "ma10": "236.1\u2197", "ma20": "230\u2198", "ma30": "229.5\u2197", "ma60": "212.2\u2197", "ma240": "195.4\u2197", "ma480": "168.5\u2197", "ma720": "166.4\u2198", "ma1200": "155.7\u2197", "ma2400": ""}}, {"t_makink": {"code": "1413", "name": "\u5b8f\u6d32", "date": "8.61", "price": -0.01, "change": -0.12, "pct": 38.0, "volume": 0.0, "ma5": "8.65\u2197", "ma10": "8.55\u2198", "ma20": "8.41\u2197", "ma30": "8.4\u2198", "ma60": "8.59\u2198", "ma240": "8.18\u2197", "ma480": "9.54\u2198", "ma720": "10.48\u2198", "ma1200": "9.09\u2197", "ma2400": "7.33\u2198"}}, {"t_makink": {"code": "3045", "name": "\u53f0\u7063\u5927", "date": "98.2", "price": 0.0, "change": 0.0, "pct": 1750.0, "volume": 0.0, "ma5": "98.52\u2197", "ma10": "98.07\u2198", "ma20": "98.28\u2198", "ma30": "98.06\u2198", "ma60": "98.04\u2197", "ma240": "101.9\u2198", "ma480": "107.2\u2198", "ma720": "107.6\u2198", "ma1200": "108.2\u2198", "ma2400": "102.4\u2197"}}, {"t_makink": {"code": "00662", "name": "\u5bcc\u90a6NASDAQ", "date": "48.29", "price": 0.97, "change": 2.05, "pct": 607.0, "volume": 0.0, "ma5": "47.54\u2197", "ma10": "47.47\u2197", "ma20": "46.93\u2197", "ma30": "47.04\u2197", "ma60": "45.45\u2197", "ma240": "41.99\u2197", "ma480": "37.31\u2197", "ma720": "34.62\u2197", "ma1200": "", "ma2400": ""}}, {"t_makink": {"code": "1464", "name": "\u5f97\u529b", "date": "17.4", "price": -0.05, "change": -0.29, "pct": 481.0, "volume": 0.0, "ma5": "17.61\u2198", "ma10": "17.56\u2198", "ma20": "17.86\u2198", "ma30": "17.9\u2198", "ma60": "18.14\u2198", "ma240": "18.81\u2197", "ma480": "21.59\u2198", "ma720": "21.89\u2198", "ma1200": "24.28\u2198", "ma2400": "19.13\u2197"}}, {"t_makink": {"code": "2882B", "name": "\u570b\u6cf0\u91d1\u4e59\u7279", "date": "62.3", "price": 0.0, "change": 0.0, "pct": 29.0, "volume": 0.0, "ma5": "62.18\u2197", "ma10": "62.14\u2197", "ma20": "62.2\u2198", "ma30": "62.35\u2198", "ma60": "62.41\u2198", "ma240": "62.83\u2197", "ma480": "63.02\u2198", "ma720": "", "ma1200": "", "ma2400": ""}}, {"t_makink": {"code": "00784B", "name": "\u5bcc\u90a6\u4e2d\u570b\u6295\u7b49\u50b5", "date": "38.2", "price": 0.15, "change": 0.39, "pct": 101.0, "volume": 0.0, "ma5": "38.21\u2198", "ma10": "38.19\u2197", "ma20": "37.95\u2197", "ma30": "38.04\u2198", "ma60": "38.6\u2198", "ma240": "39.54\u2198", "ma480": "", "ma720": "", "ma1200": "", "ma2400": ""}}, {"t_makink": {"code": "00666R", "name": "\u5bcc\u90a6\u6052\u751f\u570b\u4f01\u53cd1", "date": "10.9", "price": -0.13, "change": -1.18, "pct": 76.0, "volume": 0.0, "ma5": "11.02\u2198", "ma10": "11.01\u2197", "ma20": "10.89\u2197", "ma30": "10.87\u2198", "ma60": "11.6\u2198", "ma240": "12.44\u2198", "ma480": "12.93\u2198", "ma720": "13.2\u2198", "ma1200": "", "ma2400": ""}}, {"t_makink": {"code": "4141", "name": "\u9f8d\u71c8-KY", "date": "11.65", "price": 0.05, "change": 0.43, "pct": 83.0, "volume": 0.0, "ma5": "11.63\u2197", "ma10": "11.66\u2198", "ma20": "11.86\u2198", "ma30": "11.89\u2198", "ma60": "11.76\u2198", "ma240": "12.78\u2197", "ma480": "14.64\u2198", "ma720": "17.13\u2198", "ma1200": "23.65\u2198", "ma2400": ""}}, {"t_makink": {"code": "2474", "name": "\u53ef\u6210", "date": "211", "price": -0.5, "change": -0.24, "pct": 2801.0, "volume": 0.0, "ma5": "209.2\u2197", "ma10": "207.1\u2197", "ma20": "202.2\u2197", "ma30": "201.7\u2197", "ma60": "195\u2197", "ma240": "204.9\u2197", "ma480": "220\u2198", "ma720": "249.3\u2198", "ma1200": "264.5\u2198", "ma2400": "241.4\u2197"}}, {"t_makink": {"code": "00861", "name": "\u5143\u5927\u5168\u7403\u672a\u4f86\u901a\u8a0a", "date": "28.44", "price": 0.32, "change": 1.14, "pct": 1805.0, "volume": 0.0, "ma5": "28.21\u2197", "ma10": "27.94\u2197", "ma20": "27.42\u2197", "ma30": "27.49\u2197", "ma60": "26.02\u2197", "ma240": "23.83\u2197", "ma480": "", "ma720": "", "ma1200": "", "ma2400": ""}}, {"t_makink": {"code": "8121", "name": "\u8d8a\u5cf0", "date": "18.35", "price": -0.05, "change": -0.27, "pct": 618.0, "volume": 0.0, "ma5": "18.43\u2197", "ma10": "18.28\u2198", "ma20": "18.19\u2197", "ma30": "18.14\u2197", "ma60": "17.56\u2197", "ma240": "14.41\u2197", "ma480": "13.39\u2197", "ma720": "14.63\u2198", "ma1200": "14.5\u2197", "ma2400": "29.87\u2198"}}, {"t_makink": {"code": "912398", "name": "\u53cb\u4f73-DR", "date": "4.26", "price": -0.11, "change": -2.52, "pct": 818.0, "volume": 0.0, "ma5": "4.33\u2198", "ma10": "4.35\u2198", "ma20": "4.36\u2198", "ma30": "4.35\u2198", "ma60": "5.4\u2198", "ma240": "4.72\u2197", "ma480": "4.38\u2198", "ma720": "5.27\u2198", "ma1200": "6.11\u2198", "ma2400": "9.03\u2198"}}, {"t_makink": {"code": "8027", "name": "\u9226\u6607", "date": "92", "price": 0.1, "change": 0.11, "pct": 634.0, "volume": 0.0, "ma5": "90.9\u2197", "ma10": "90.33\u2198", "ma20": "88.63\u2197", "ma30": "88.39\u2197", "ma60": "82.76\u2197", "ma240": "65.02\u2197", "ma480": "47.67\u2197", "ma720": "43.9\u2197", "ma1200": "36.86\u2197", "ma2400": ""}}, {"t_makink": {"code": "8072", "name": "\u965e\u6cf0", "date": "28.6", "price": -0.1, "change": -0.35, "pct": 51.0, "volume": 0.0, "ma5": "28.78\u2197", "ma10": "28.67\u2198", "ma20": "28.72\u2198", "ma30": "28.65\u2197", "ma60": "28.99\u2198", "ma240": "27.47\u2197", "ma480": "24.13\u2197", "ma720": "23.49\u2197", "ma1200": "23.05\u2197", "ma2400": "49.02\u2198"}}, {"t_makink": {"code": "2897A", "name": "\u738b\u9053\u9280\u7532\u7279", "date": "10.2", "price": 0.05, "change": 0.49, "pct": 14.0, "volume": 0.0, "ma5": "10.18\u2197", "ma10": "10.18\u2192", "ma20": "10.19\u2197", "ma30": "10.16\u2197", "ma60": "10.15\u2192", "ma240": "10.19\u2197", "ma480": "10.32\u2198", "ma720": "", "ma1200": "", "ma2400": ""}}, {"t_makink": {"code": "1724", "name": "\u53f0\u785d", "date": "14.7", "price": 1.3, "change": 9.7, "pct": 139.0, "volume": 0.0, "ma5": "13.4\u2197", "ma10": "13.04\u2197", "ma20": "12.86\u2197", "ma30": "12.82\u2197", "ma60": "12.81\u2197", "ma240": "12.55\u2197", "ma480": "12.76\u2197", "ma720": "13.01\u2197", "ma1200": "14.16\u2198", "ma2400": "16.9\u2197"}}, {"t_makink": {"code": "00762", "name": "\u5143\u5927\u5168\u7403AI", "date": "37.59", "price": 0.92, "change": 2.51, "pct": 649.0, "volume": 0.0, "ma5": "36.81\u2197", "ma10": "36.87\u2198", "ma20": "36.54\u2197", "ma30": "36.44\u2197", "ma60": "34.65\u2197", "ma240": "31.33\u2197", "ma480": "27.59\u2197", "ma720": "", "ma1200": "", "ma2400": ""}}, {"t_makink": {"code": "2358", "name": "\u5ef7\u946b", "date": "14", "price": -0.05, "change": -0.36, "pct": 140.0, "volume": 0.0, "ma5": "14.21\u2198", "ma10": "14.17\u2197", "ma20": "14.09\u2198", "ma30": "14.13\u2198", "ma60": "14.68\u2198", "ma240": "14.32\u2197", "ma480": "14.72\u2198", "ma720": "16.57\u2198", "ma1200": "16.02\u2197", "ma2400": "13.89\u2197"}}, {"t_makink": {"code": "3205", "name": "\u4f70\u7814", "date": "32.1", "price": -0.2, "change": -0.62, "pct": 35.0, "volume": 0.0, "ma5": "31.95\u2197", "ma10": "31.85\u2197", "ma20": "31.87\u2197", "ma30": "31.96\u2198", "ma60": "33.36\u2198", "ma240": "36.55\u2197", "ma480": "43.32\u2198", "ma720": "47.34\u2198", "ma1200": "80.16\u2198", "ma2400": "66.02\u2197"}}, {"t_makink": {"code": "3543", "name": "\u5dde\u5de7", "date": "30.8", "price": 0.2, "change": 0.65, "pct": 136.0, "volume": 0.0, "ma5": "30.8\u2197", "ma10": "30.56\u2197", "ma20": "30.11\u2197", "ma30": "30.03\u2197", "ma60": "27.03\u2197", "ma240": "", "ma480": "", "ma720": "", "ma1200": "", "ma2400": ""}}, {"t_makink": {"code": "2330", "name": "\u53f0\u7a4d\u96fb", "date": "602", "price": 15.0, "change": 2.56, "pct": 45973.0, "volume": 0.0, "ma5": "595\u2197", "ma10": "590.4\u2192", "ma20": "597.6\u2198", "ma30": "599.3\u2197", "ma60": "535.3\u2197", "ma240": "444\u2197", "ma480": "361.6\u2197", "ma720": "319.1\u2197", "ma1200": "270.3\u2197", "ma2400": "188.3\u2197"}}, {"t_makink": {"code": "00860B", "name": "\u7fa4\u76ca1-5\u5e74IG\u50b5", "date": "38.07", "price": 0.08, "change": 0.21, "pct": 100.0, "volume": 0.0, "ma5": "38.08\u2198", "ma10": "38.06\u2197", "ma20": "37.82\u2197", "ma30": "37.71\u2197", "ma60": "38.05\u2198", "ma240": "38.73\u2198", "ma480": "", "ma720": "", "ma1200": "", "ma2400": ""}}, {"t_makink": {"code": "1459", "name": "\u806f\u767c", "date": "8.95", "price": -0.05, "change": -0.56, "pct": 826.0, "volume": 0.0, "ma5": "8.91\u2197", "ma10": "8.7\u2197", "ma20": "8.51\u2197", "ma30": "8.48\u2197", "ma60": "8.36\u2197", "ma240": "7.87\u2197", "ma480": "7.55\u2197", "ma720": "7.9\u2197", "ma1200": "8.19\u2198", "ma2400": "9.42\u2198"}}, {"t_makink": {"code": "2528", "name": "\u7687\u666e", "date": "23.5", "price": -0.2, "change": -0.84, "pct": 20.0, "volume": 0.0, "ma5": "23.47\u2197", "ma10": "23.32\u2197", "ma20": "23.19\u2197", "ma30": "23.26\u2197", "ma60": "23.71\u2198", "ma240": "22.41\u2197", "ma480": "20.33\u2197", "ma720": "18.68\u2197", "ma1200": "15.93\u2197", "ma2400": "13.96\u2197"}}, {"t_makink": {"code": "6265", "name": "\u65b9\u571f\u6636", "date": "8.09", "price": 0.03, "change": 0.37, "pct": 197.0, "volume": 0.0, "ma5": "8.07\u2198", "ma10": "8.1\u2197", "ma20": "7.83\u2197", "ma30": "7.81\u2197", "ma60": "7.27\u2197", "ma240": "6.65\u2197", "ma480": "6.49\u2197", "ma720": "6.43\u2197", "ma1200": "6.71\u2197", "ma2400": "7.45\u2198"}}, {"t_makink": {"code": "3290", "name": "\u6771\u6d66", "date": "15.6", "price": 0.35, "change": 2.3, "pct": 258.0, "volume": 0.0, "ma5": "15.42\u2197", "ma10": "15.36\u2197", "ma20": "14.98\u2197", "ma30": "14.94\u2197", "ma60": "15.11\u2197", "ma240": "14.36\u2197", "ma480": "17.36\u2198", "ma720": "17.65\u2197", "ma1200": "16.59\u2197", "ma2400": "18.59\u2198"}}, {"t_makink": {"code": "2542", "name": "\u8208\u5bcc\u767c", "date": "43.55", "price": 0.05, "change": 0.11, "pct": 2992.0, "volume": 0.0, "ma5": "43.51\u2198", "ma10": "43.57\u2198", "ma20": "44.39\u2198", "ma30": "44.52\u2198", "ma60": "44.02\u2198", "ma240": "43.86\u2197", "ma480": "45.61\u2198", "ma720": "45.87\u2198", "ma1200": "46.29\u2197", "ma2400": "52.29\u2198"}}]